{"nodes": [{"id": "c_users_jimi_documents_app_blog_server_services_audiencesegments_js", "label": "audienceSegments.js", "file_type": "code", "source_file": "C:\\Users\\jimi\\Documents\\APP\\Blog\\server\\services\\audienceSegments.js", "source_location": "L1"}, {"id": "services_audiencesegments_segment_definitions", "label": "SEGMENT_DEFINITIONS", "file_type": "code", "source_file": "C:\\Users\\jimi\\Documents\\APP\\Blog\\server\\services\\audienceSegments.js", "source_location": "L3"}, {"id": "services_audiencesegments_segment_ids", "label": "SEGMENT_IDS", "file_type": "code", "source_file": "C:\\Users\\jimi\\Documents\\APP\\Blog\\server\\services\\audienceSegments.js", "source_location": "L41"}, {"id": "services_audiencesegments_normalizesegmentid", "label": "normalizeSegmentId()", "file_type": "code", "source_file": "C:\\Users\\jimi\\Documents\\APP\\Blog\\server\\services\\audienceSegments.js", "source_location": "L43"}, {"id": "services_audiencesegments_totime", "label": "toTime()", "file_type": "code", "source_file": "C:\\Users\\jimi\\Documents\\APP\\Blog\\server\\services\\audienceSegments.js", "source_location": "L48"}, {"id": "services_audiencesegments_dayssince", "label": "daysSince()", "file_type": "code", "source_file": "C:\\Users\\jimi\\Documents\\APP\\Blog\\server\\services\\audienceSegments.js", "source_location": "L54"}, {"id": "services_audiencesegments_getfanid", "label": "getFanId()", "file_type": "code", "source_file": "C:\\Users\\jimi\\Documents\\APP\\Blog\\server\\services\\audienceSegments.js", "source_location": "L60"}, {"id": "services_audiencesegments_getlastactivity", "label": "getLastActivity()", "file_type": "code", "source_file": "C:\\Users\\jimi\\Documents\\APP\\Blog\\server\\services\\audienceSegments.js", "source_location": "L64"}, {"id": "services_audiencesegments_activerows", "label": "activeRows()", "file_type": "code", "source_file": "C:\\Users\\jimi\\Documents\\APP\\Blog\\server\\services\\audienceSegments.js", "source_location": "L73"}, {"id": "services_audiencesegments_selectfanidsforsegment", "label": "selectFanIdsForSegment()", "file_type": "code", "source_file": "C:\\Users\\jimi\\Documents\\APP\\Blog\\server\\services\\audienceSegments.js", "source_location": "L77"}], "edges": [{"source": "c_users_jimi_documents_app_blog_server_services_audiencesegments_js", "target": "services_audiencesegments_segment_definitions", "relation": "contains", "confidence": "EXTRACTED", "source_file": "C:\\Users\\jimi\\Documents\\APP\\Blog\\server\\services\\audienceSegments.js", "source_location": "L3", "weight": 1.0}, {"source": "c_users_jimi_documents_app_blog_server_services_audiencesegments_js", "target": "services_audiencesegments_segment_ids", "relation": "contains", "confidence": "EXTRACTED", "source_file": "C:\\Users\\jimi\\Documents\\APP\\Blog\\server\\services\\audienceSegments.js", "source_location": "L41", "weight": 1.0}, {"source": "c_users_jimi_documents_app_blog_server_services_audiencesegments_js", "target": "services_audiencesegments_normalizesegmentid", "relation": "contains", "confidence": "EXTRACTED", "source_file": "C:\\Users\\jimi\\Documents\\APP\\Blog\\server\\services\\audienceSegments.js", "source_location": "L43", "weight": 1.0}, {"source": "c_users_jimi_documents_app_blog_server_services_audiencesegments_js", "target": "services_audiencesegments_totime", "relation": "contains", "confidence": "EXTRACTED", "source_file": "C:\\Users\\jimi\\Documents\\APP\\Blog\\server\\services\\audienceSegments.js", "source_location": "L48", "weight": 1.0}, {"source": "c_users_jimi_documents_app_blog_server_services_audiencesegments_js", "target": "services_audiencesegments_dayssince", "relation": "contains", "confidence": "EXTRACTED", "source_file": "C:\\Users\\jimi\\Documents\\APP\\Blog\\server\\services\\audienceSegments.js", "source_location": "L54", "weight": 1.0}, {"source": "c_users_jimi_documents_app_blog_server_services_audiencesegments_js", "target": "services_audiencesegments_getfanid", "relation": "contains", "confidence": "EXTRACTED", "source_file": "C:\\Users\\jimi\\Documents\\APP\\Blog\\server\\services\\audienceSegments.js", "source_location": "L60", "weight": 1.0}, {"source": "c_users_jimi_documents_app_blog_server_services_audiencesegments_js", "target": "services_audiencesegments_getlastactivity", "relation": "contains", "confidence": "EXTRACTED", "source_file": "C:\\Users\\jimi\\Documents\\APP\\Blog\\server\\services\\audienceSegments.js", "source_location": "L64", "weight": 1.0}, {"source": "c_users_jimi_documents_app_blog_server_services_audiencesegments_js", "target": "services_audiencesegments_activerows", "relation": "contains", "confidence": "EXTRACTED", "source_file": "C:\\Users\\jimi\\Documents\\APP\\Blog\\server\\services\\audienceSegments.js", "source_location": "L73", "weight": 1.0}, {"source": "c_users_jimi_documents_app_blog_server_services_audiencesegments_js", "target": "services_audiencesegments_selectfanidsforsegment", "relation": "contains", "confidence": "EXTRACTED", "source_file": "C:\\Users\\jimi\\Documents\\APP\\Blog\\server\\services\\audienceSegments.js", "source_location": "L77", "weight": 1.0}, {"source": "services_audiencesegments_dayssince", "target": "services_audiencesegments_totime", "relation": "calls", "context": "call", "confidence": "EXTRACTED", "source_file": "C:\\Users\\jimi\\Documents\\APP\\Blog\\server\\services\\audienceSegments.js", "source_location": "L55", "weight": 1.0}, {"source": "services_audiencesegments_getlastactivity", "target": "services_audiencesegments_totime", "relation": "calls", "context": "call", "confidence": "EXTRACTED", "source_file": "C:\\Users\\jimi\\Documents\\APP\\Blog\\server\\services\\audienceSegments.js", "source_location": "L66", "weight": 1.0}, {"source": "services_audiencesegments_selectfanidsforsegment", "target": "services_audiencesegments_normalizesegmentid", "relation": "calls", "context": "call", "confidence": "EXTRACTED", "source_file": "C:\\Users\\jimi\\Documents\\APP\\Blog\\server\\services\\audienceSegments.js", "source_location": "L78", "weight": 1.0}, {"source": "services_audiencesegments_selectfanidsforsegment", "target": "services_audiencesegments_activerows", "relation": "calls", "context": "call", "confidence": "EXTRACTED", "source_file": "C:\\Users\\jimi\\Documents\\APP\\Blog\\server\\services\\audienceSegments.js", "source_location": "L80", "weight": 1.0}], "raw_calls": [{"caller_nid": "services_audiencesegments_normalizesegmentid", "callee": "trim", "is_member_call": true, "source_file": "C:\\Users\\jimi\\Documents\\APP\\Blog\\server\\services\\audienceSegments.js", "source_location": "L44"}, {"caller_nid": "services_audiencesegments_normalizesegmentid", "callee": "String", "is_member_call": false, "source_file": "C:\\Users\\jimi\\Documents\\APP\\Blog\\server\\services\\audienceSegments.js", "source_location": "L44"}, {"caller_nid": "services_audiencesegments_normalizesegmentid", "callee": "has", "is_member_call": true, "source_file": "C:\\Users\\jimi\\Documents\\APP\\Blog\\server\\services\\audienceSegments.js", "source_location": "L45"}, {"caller_nid": "services_audiencesegments_totime", "callee": "getTime", "is_member_call": true, "source_file": "C:\\Users\\jimi\\Documents\\APP\\Blog\\server\\services\\audienceSegments.js", "source_location": "L50"}, {"caller_nid": "services_audiencesegments_totime", "callee": "isFinite", "is_member_call": true, "source_file": "C:\\Users\\jimi\\Documents\\APP\\Blog\\server\\services\\audienceSegments.js", "source_location": "L51"}, {"caller_nid": "services_audiencesegments_dayssince", "callee": "floor", "is_member_call": true, "source_file": "C:\\Users\\jimi\\Documents\\APP\\Blog\\server\\services\\audienceSegments.js", "source_location": "L57"}, {"caller_nid": "services_audiencesegments_dayssince", "callee": "getTime", "is_member_call": true, "source_file": "C:\\Users\\jimi\\Documents\\APP\\Blog\\server\\services\\audienceSegments.js", "source_location": "L57"}, {"caller_nid": "services_audiencesegments_getlastactivity", "callee": "max", "is_member_call": true, "source_file": "C:\\Users\\jimi\\Documents\\APP\\Blog\\server\\services\\audienceSegments.js", "source_location": "L65"}, {"caller_nid": "services_audiencesegments_activerows", "callee": "filter", "is_member_call": true, "source_file": "C:\\Users\\jimi\\Documents\\APP\\Blog\\server\\services\\audienceSegments.js", "source_location": "L74"}, {"caller_nid": "services_audiencesegments_activerows", "callee": "isArray", "is_member_call": true, "source_file": "C:\\Users\\jimi\\Documents\\APP\\Blog\\server\\services\\audienceSegments.js", "source_location": "L74"}, {"caller_nid": "services_audiencesegments_selectfanidsforsegment", "callee": "now", "is_member_call": true, "source_file": "C:\\Users\\jimi\\Documents\\APP\\Blog\\server\\services\\audienceSegments.js", "source_location": "L79"}, {"caller_nid": "services_audiencesegments_selectfanidsforsegment", "callee": "filter", "is_member_call": true, "source_file": "C:\\Users\\jimi\\Documents\\APP\\Blog\\server\\services\\audienceSegments.js", "source_location": "L84"}, {"caller_nid": "services_audiencesegments_selectfanidsforsegment", "callee": "sort", "is_member_call": true, "source_file": "C:\\Users\\jimi\\Documents\\APP\\Blog\\server\\services\\audienceSegments.js", "source_location": "L86"}, {"caller_nid": "services_audiencesegments_selectfanidsforsegment", "callee": "filter", "is_member_call": true, "source_file": "C:\\Users\\jimi\\Documents\\APP\\Blog\\server\\services\\audienceSegments.js", "source_location": "L86"}, {"caller_nid": "services_audiencesegments_selectfanidsforsegment", "callee": "slice", "is_member_call": true, "source_file": "C:\\Users\\jimi\\Documents\\APP\\Blog\\server\\services\\audienceSegments.js", "source_location": "L89"}, {"caller_nid": "services_audiencesegments_selectfanidsforsegment", "callee": "max", "is_member_call": true, "source_file": "C:\\Users\\jimi\\Documents\\APP\\Blog\\server\\services\\audienceSegments.js", "source_location": "L89"}, {"caller_nid": "services_audiencesegments_selectfanidsforsegment", "callee": "ceil", "is_member_call": true, "source_file": "C:\\Users\\jimi\\Documents\\APP\\Blog\\server\\services\\audienceSegments.js", "source_location": "L89"}, {"caller_nid": "services_audiencesegments_selectfanidsforsegment", "callee": "filter", "is_member_call": true, "source_file": "C:\\Users\\jimi\\Documents\\APP\\Blog\\server\\services\\audienceSegments.js", "source_location": "L91"}, {"caller_nid": "services_audiencesegments_selectfanidsforsegment", "callee": "filter", "is_member_call": true, "source_file": "C:\\Users\\jimi\\Documents\\APP\\Blog\\server\\services\\audienceSegments.js", "source_location": "L96"}, {"caller_nid": "services_audiencesegments_selectfanidsforsegment", "callee": "filter", "is_member_call": true, "source_file": "C:\\Users\\jimi\\Documents\\APP\\Blog\\server\\services\\audienceSegments.js", "source_location": "L98"}, {"caller_nid": "services_audiencesegments_selectfanidsforsegment", "callee": "filter", "is_member_call": true, "source_file": "C:\\Users\\jimi\\Documents\\APP\\Blog\\server\\services\\audienceSegments.js", "source_location": "L100"}, {"caller_nid": "services_audiencesegments_selectfanidsforsegment", "callee": "map", "is_member_call": true, "source_file": "C:\\Users\\jimi\\Documents\\APP\\Blog\\server\\services\\audienceSegments.js", "source_location": "L105"}]}